elektron_mcp/__init__.py
elektron_mcp/main.py
elektron_mcp/digitone/__init__.py
elektron_mcp/digitone/config/__init__.py
elektron_mcp/digitone/config/digitone_config.py
elektron_mcp/digitone/constants/__init__.py
elektron_mcp/digitone/constants/amp.py
elektron_mcp/digitone/constants/filters.py
elektron_mcp/digitone/constants/fm_drum.py
elektron_mcp/digitone/constants/fm_tone.py
elektron_mcp/digitone/constants/fx.py
elektron_mcp/digitone/constants/lfo.py
elektron_mcp/digitone/constants/swarmer.py
elektron_mcp/digitone/constants/wavetone.py
elektron_mcp/digitone/controller/__init__.py
elektron_mcp/digitone/controller/amp_fx_controller.py
elektron_mcp/digitone/controller/base_synth_controller.py
elektron_mcp/digitone/controller/filter_controller.py
elektron_mcp/digitone/controller/fm_drum_controller.py
elektron_mcp/digitone/controller/fm_tone_controller.py
elektron_mcp/digitone/controller/lfo_controller.py
elektron_mcp/digitone/controller/swarmer_controller.py
elektron_mcp/digitone/controller/wavetone_controller.py
elektron_mcp/digitone/models/__init__.py
elektron_mcp/digitone/models/models.py
elektron_mcp/digitone/utils/__init__.py
elektron_mcp/digitone/utils/parameter_utils.py
elektron_mcp/mcp_server/__init__.py
elektron_mcp/mcp_server/server.py
elektron_mcp/midi/__init__.py
elektron_mcp/midi/digitone_midi.py
elektron_mcp/tools/__init__.py
elektron_mcp/tools/amp_tool.py
elektron_mcp/tools/filter_tool.py
elektron_mcp/tools/fx_tool.py
elektron_mcp/tools/lfo_tool.py
elektron_mcp/tools/wavetone_tool.py
elektron_mcp-0.2.4.dist-info/METADATA
elektron_mcp-0.2.4.dist-info/WHEEL
elektron_mcp-0.2.4.dist-info/entry_points.txt
elektron_mcp-0.2.4.dist-info/RECORD
