Metadata-Version: 2.4
Name: elektron-mcp
Version: 0.2.4
Summary: MPC to control Elektron machines (Digitakt 2, Digitone 2)
Project-URL: Homepage, https://github.com/zerubeus/elektron-mcp
Project-URL: Bug Tracker, https://github.com/zerubeus/elektron-mcp/issues
Author-email: zerubeus <zerubeus@gmail.com>
License: MIT
Classifier: License :: OSI Approved :: MIT License
Classifier: Operating System :: OS Independent
Classifier: Programming Language :: Python :: 3
Requires-Python: >=3.12
Requires-Dist: mcp[cli]>=1.5.0
Requires-Dist: mido>=1.3.1
Requires-Dist: pydantic>=2.10.6
Requires-Dist: python-rtmidi>=1.5.7
